{
  "swagger" : "2.0",
  "info" : {
    "version" : "1.0.0",
    "title" : "OpenMRS FHIR REST Services",
    "description" : "Auto-generated documentation for OpenMRS FHIR Rest services",
    "termsOfService" : "https://www.mozilla.org/en-US/MPL/2.0/",
    "contact" : {
      "name" : "OpenMRS FHIR Module Team",
      "url" : "https://talk.openmrs.org/c/dev",
      "email" : "community@openmrs.org"
    },
    "license" : {
      "name" : "Mozilla Public License, v. 2.0",
      "url" : "http://openmrs.org/license/"
    }
  },
  "host" : "localhost:8080",
  "basePath" : "/openmrs/ws/fhir",
  "consumes" : [ "application/xml", "application/json" ],
  "produces" : [ "application/json", "application/xml", "application/xml+fhir", "application/json+fhir" ],
  "paths" : {
    "/Encounter" : {
      "post" : {
        "summary" : "Create Encounter resource from the content of the request",
        "produces" : [ "application/json", "application/xml", "application/xml+fhir", "application/json+fhir" ],
        "parameters" : [ {
          "name" : "body",
          "in" : "body",
          "description" : "Encounter resource object",
          "required" : true,
          "schema" : {
            "$ref" : "#/definitions/Encounter"
          }
        } ],
        "responses" : {
          "200" : {
            "description" : "Returns success operation outcome",
            "schema" : {
              "type" : "object",
              "$ref" : "#/definitions/OperationOutcome"
            }
          },
          "404" : {
            "description" : "When error occurred",
            "schema" : {
              "type" : "object",
              "$ref" : "#/definitions/GeneralError"
            },
            "examples" : {
              "application/json" : "{}"
            }
          }
        }
      },
      "get" : {
        "summary" : "Returns Encounter matching results",
        "produces" : [ "application/json", "application/xml", "application/xml+fhir", "application/json+fhir" ],
        "parameters" : [ {
          "name" : "patient",
          "in" : "query",
          "description" : "",
          "required" : false,
          "type" : "string"
        }, {
          "name" : "part-of",
          "in" : "query",
          "description" : "",
          "required" : false,
          "type" : "string"
        }, {
          "name" : "_id",
          "in" : "query",
          "description" : "The ID of the resource",
          "required" : false,
          "type" : "string"
        } ],
        "responses" : {
          "200" : {
            "description" : "Bundle of Encounter resources",
            "schema" : {
              "type" : "array",
              "$ref" : "#/definitions/Encounter"
            },
            "examples" : {
              "application/json" : "{\n    resourceType: \"Encounter\",\n    status: \"finished\",\n    class: \"inpatient\",\n    subject: {\n        reference: \"Patient/dd738d54-1691-11df-97a5-7038c432aabf\",\n        display: \"Daisylene Ekeno(Identifier:1865TU-8)\"\n    },\n    participant: [{\n            individual: {\n                reference: \"Practitioner/bf218490-1691-11df-97a5-7038c432aabf\",\n                display: \"Super User(Identifier:admin)\"\n            }\n        }],\n    period: {\n        start: \"2006-02-07T00:00:00\",\n        end: \"2006-02-07T00:00:00\"\n    },\n    location: [\n          {\n            location: {\n                reference: \"Location/8d6c993e-c2cc-11de-8d13-0010c6dffd0f\",\n                display: \"Inpatient Ward\"\n            },\n            period: {\n                start: \"2006-02-07T00:00:00\",\n                end: \"2006-02-07T00:00:00\"\n            }\n        }]\n}"
            }
          },
          "404" : {
            "description" : "When error occurred",
            "schema" : {
              "type" : "object",
              "$ref" : "#/definitions/GeneralError"
            },
            "examples" : {
              "application/json" : "{}"
            }
          }
        }
      }
    },
    "/AllergyIntolerance/{id}" : {
      "get" : {
        "summary" : "Returns AllergyIntolerance details of given id",
        "produces" : [ "application/json", "application/xml", "application/xml+fhir", "application/json+fhir" ],
        "parameters" : [ {
          "name" : "id",
          "in" : "path",
          "description" : "Id of the  AllergyIntolerance resource",
          "required" : true,
          "type" : "string"
        } ],
        "responses" : {
          "200" : {
            "description" : "Returns AllergyIntolerance details of given id",
            "schema" : {
              "type" : "object",
              "$ref" : "#/definitions/AllergyIntolerance"
            },
            "examples" : {
              "application/json" : "{}"
            }
          },
          "404" : {
            "description" : "When error occurred",
            "schema" : {
              "type" : "object",
              "$ref" : "#/definitions/GeneralError"
            },
            "examples" : {
              "application/json" : "{}"
            }
          }
        }
      }
    },
    "/DiagnosticReport" : {
      "post" : {
        "summary" : "Create DiagnosticReport resource from the content of the request",
        "produces" : [ "application/json", "application/xml", "application/xml+fhir", "application/json+fhir" ],
        "parameters" : [ {
          "name" : "body",
          "in" : "body",
          "description" : "DiagnosticReport resource object",
          "required" : true,
          "schema" : {
            "$ref" : "#/definitions/DiagnosticReport"
          }
        } ],
        "responses" : {
          "200" : {
            "description" : "Returns success operation outcome",
            "schema" : {
              "type" : "object",
              "$ref" : "#/definitions/OperationOutcome"
            }
          },
          "404" : {
            "description" : "When error occurred",
            "schema" : {
              "type" : "object",
              "$ref" : "#/definitions/GeneralError"
            },
            "examples" : {
              "application/json" : "{}"
            }
          }
        }
      },
      "get" : {
        "summary" : "Returns DiagnosticReport matching results",
        "produces" : [ "application/json", "application/xml", "application/xml+fhir", "application/json+fhir" ],
        "parameters" : [ {
          "name" : "subject",
          "in" : "query",
          "description" : "The subject of the report",
          "required" : false,
          "type" : "string"
        }, {
          "name" : "service",
          "in" : "query",
          "description" : "Which diagnostic discipline/department created the report",
          "required" : false,
          "type" : "string"
        } ],
        "responses" : {
          "200" : {
            "description" : "Bundle of DiagnosticReport resources",
            "schema" : {
              "type" : "array",
              "$ref" : "#/definitions/DiagnosticReport"
            }
          },
          "404" : {
            "description" : "When error occurred",
            "schema" : {
              "type" : "object",
              "$ref" : "#/definitions/GeneralError"
            },
            "examples" : {
              "application/json" : "{}"
            }
          }
        }
      }
    },
    "/Person" : {
      "post" : {
        "summary" : "Create Person resource from the content of the request",
        "produces" : [ "application/json", "application/xml", "application/xml+fhir", "application/json+fhir" ],
        "parameters" : [ {
          "name" : "body",
          "in" : "body",
          "description" : "Person resource object",
          "required" : true,
          "schema" : {
            "$ref" : "#/definitions/Person"
          }
        } ],
        "responses" : {
          "200" : {
            "description" : "Returns success operation outcome",
            "schema" : {
              "type" : "object",
              "$ref" : "#/definitions/OperationOutcome"
            }
          },
          "404" : {
            "description" : "When error occurred",
            "schema" : {
              "type" : "object",
              "$ref" : "#/definitions/GeneralError"
            },
            "examples" : {
              "application/json" : "{}"
            }
          }
        }
      },
      "get" : {
        "summary" : "Returns Person matching results",
        "produces" : [ "application/json", "application/xml", "application/xml+fhir", "application/json+fhir" ],
        "parameters" : [ {
          "name" : "birthdate",
          "in" : "query",
          "description" : "The person's date of birth",
          "required" : false,
          "type" : "string"
        }, {
          "name" : "gender",
          "in" : "query",
          "description" : "The gender of the person",
          "required" : false,
          "type" : "string"
        }, {
          "name" : "name",
          "in" : "query",
          "description" : "A portion of name in any name part",
          "required" : false,
          "type" : "string"
        }, {
          "name" : "_id",
          "in" : "query",
          "description" : "The ID of the resource",
          "required" : false,
          "type" : "string"
        } ],
        "responses" : {
          "200" : {
            "description" : "Bundle of Person resources",
            "schema" : {
              "type" : "array",
              "$ref" : "#/definitions/Person"
            },
            "examples" : {
              "application/json" : "{\n  \"resourceType\": \"Person\",\n  \"id\": \"dda12af7-1691-11df-97a5-7038c432aabf\",\n  \"name\": [\n    {\n      \"use\": \"official\",\n      \"family\": [\n        \"Chalmers\"\n      ],\n      \"given\": [\n        \"Peter\",\n        \"James\"\n      ]\n    },\n    {\n      \"use\": \"usual\",\n      \"given\": [\n        \"Jim\"\n      ]\n    }\n  ],\n  \"gender\": \"male\",\n  \"birthDate\": \"1974-12-25\",\n  \"address\": [\n    {\n      \"use\": \"home\",\n      \"line\": [\n        \"534 Erewhon St\"\n      ],\n      \"city\": \"PleasantVille\",\n      \"state\": \"Vic\",\n      \"postalCode\": \"3999\"\n    }\n  ],\n  \"active\": true\n}"
            }
          },
          "404" : {
            "description" : "When error occurred",
            "schema" : {
              "type" : "object",
              "$ref" : "#/definitions/GeneralError"
            },
            "examples" : {
              "application/json" : "{}"
            }
          }
        }
      }
    },
    "/Observation/{id}" : {
      "get" : {
        "summary" : "Returns Observation details of given id",
        "produces" : [ "application/json", "application/xml", "application/xml+fhir", "application/json+fhir" ],
        "parameters" : [ {
          "name" : "id",
          "in" : "path",
          "description" : "Id of the  Observation resource",
          "required" : true,
          "type" : "string"
        } ],
        "responses" : {
          "200" : {
            "description" : "Returns Observation details of given id",
            "schema" : {
              "type" : "object",
              "$ref" : "#/definitions/Observation"
            },
            "examples" : {
              "application/json" : "{}"
            }
          },
          "404" : {
            "description" : "When error occurred",
            "schema" : {
              "type" : "object",
              "$ref" : "#/definitions/GeneralError"
            },
            "examples" : {
              "application/json" : "{}"
            }
          }
        }
      },
      "delete" : {
        "summary" : "Returns Observation details of given id",
        "produces" : [ "application/json", "application/xml", "application/xml+fhir", "application/json+fhir" ],
        "parameters" : [ {
          "name" : "id",
          "in" : "path",
          "description" : "Id of the  Observation resource",
          "required" : true,
          "type" : "string"
        } ],
        "responses" : {
          "200" : {
            "description" : "Delete Observation details of given id"
          },
          "404" : {
            "description" : "When error occurred",
            "schema" : {
              "type" : "object",
              "$ref" : "#/definitions/GeneralError"
            },
            "examples" : {
              "application/json" : "{}"
            }
          }
        }
      },
      "put" : {
        "summary" : "Update Observation resource from the content of the request",
        "produces" : [ "application/json", "application/xml", "application/xml+fhir", "application/json+fhir" ],
        "parameters" : [ {
          "name" : "body",
          "in" : "body",
          "description" : "Observation resource object",
          "required" : true,
          "schema" : {
            "$ref" : "#/definitions/Observation"
          }
        }, {
          "name" : "id",
          "in" : "path",
          "description" : "Id of the  Observation resource",
          "required" : true,
          "type" : "string"
        } ],
        "responses" : {
          "200" : {
            "description" : "Returns success operation outcome",
            "schema" : {
              "type" : "object",
              "$ref" : "#/definitions/OperationOutcome"
            }
          },
          "404" : {
            "description" : "When error occurred",
            "schema" : {
              "type" : "object",
              "$ref" : "#/definitions/GeneralError"
            },
            "examples" : {
              "application/json" : "{}"
            }
          }
        }
      }
    },
    "/Observation" : {
      "post" : {
        "summary" : "Create Observation resource from the content of the request",
        "produces" : [ "application/json", "application/xml", "application/xml+fhir", "application/json+fhir" ],
        "parameters" : [ {
          "name" : "body",
          "in" : "body",
          "description" : "Observation resource object",
          "required" : true,
          "schema" : {
            "$ref" : "#/definitions/Observation"
          }
        } ],
        "responses" : {
          "200" : {
            "description" : "Returns success operation outcome",
            "schema" : {
              "type" : "object",
              "$ref" : "#/definitions/OperationOutcome"
            }
          },
          "404" : {
            "description" : "When error occurred",
            "schema" : {
              "type" : "object",
              "$ref" : "#/definitions/GeneralError"
            },
            "examples" : {
              "application/json" : "{}"
            }
          }
        }
      },
      "get" : {
        "summary" : "Returns Observation matching results",
        "produces" : [ "application/json", "application/xml", "application/xml+fhir", "application/json+fhir" ],
        "parameters" : [ {
          "name" : "date",
          "in" : "query",
          "description" : "Obtained date/time. If the obtained element is a period, a date that falls in the period",
          "required" : false,
          "type" : "string"
        }, {
          "name" : "code",
          "in" : "query",
          "description" : "The code of the observation type",
          "required" : false,
          "type" : "string"
        }, {
          "name" : "subject",
          "in" : "query",
          "description" : "The subject that the observation is about",
          "required" : false,
          "type" : "string"
        }, {
          "name" : "patient",
          "in" : "query",
          "description" : "The subject that the observation is about (if patient)",
          "required" : false,
          "type" : "string"
        }, {
          "name" : "value-concept",
          "in" : "query",
          "description" : "The value of the observation, if the value is a CodeableConcept",
          "required" : false,
          "type" : "string"
        }, {
          "name" : "_id",
          "in" : "query",
          "description" : "The ID of the resource",
          "required" : false,
          "type" : "string"
        } ],
        "responses" : {
          "200" : {
            "description" : "Bundle of Observation resources",
            "schema" : {
              "type" : "array",
              "$ref" : "#/definitions/Observation"
            },
            "examples" : {
              "application/json" : "{}"
            }
          },
          "404" : {
            "description" : "When error occurred",
            "schema" : {
              "type" : "object",
              "$ref" : "#/definitions/GeneralError"
            },
            "examples" : {
              "application/json" : "{}"
            }
          }
        }
      }
    },
    "/FamilyMemberHistory/{id}" : {
      "get" : {
        "summary" : "Returns FamilyMemberHistory details of given id",
        "produces" : [ "application/json", "application/xml", "application/xml+fhir", "application/json+fhir" ],
        "parameters" : [ {
          "name" : "id",
          "in" : "path",
          "description" : "Id of the  FamilyMemberHistory resource",
          "required" : true,
          "type" : "string"
        } ],
        "responses" : {
          "200" : {
            "description" : "Returns FamilyMemberHistory details of given id",
            "schema" : {
              "type" : "object",
              "$ref" : "#/definitions/FamilyMemberHistory"
            },
            "examples" : {
              "application/json" : "{\n  \"resourceType\": \"FamilyHistory\",\n  \"id\": \"dda12af7-1691-11df-97a5-7038c432aabf\",\n  \"patient\": {\n    \"reference\": \"Patient/example\",\n    \"display\": \"Peter Patient\"\n  },\n  \"relation\": [\n    {\n      \"relationship\": {\n        \"coding\": [\n          {\n            \"system\": \"http://hl7.org/fhir/familial-relationship\",\n            \"code\": \"father\"\n          }\n        ]\n      },\n      \"condition\": [\n        {\n          \"type\": {\n            \"coding\": [\n              {\n                \"system\": \"http://snomed.info/sct\",\n                \"code\": \"315619001\",\n                \"display\": \"Myocardial Infarction\"\n              }\n            ],\n            \"text\": \"Heart Attack\"\n          },\n          \"onsetAge\": {\n            \"value\": 74,\n            \"units\": \"a\",\n            \"system\": \"http://unitsofmeasure.org\"\n          },\n          \"note\": \"Was fishing at the time. At least he went doing someting he loved.\"\n        }\n      ]\n    }\n  ]\n}"
            }
          },
          "404" : {
            "description" : "When error occurred",
            "schema" : {
              "type" : "object",
              "$ref" : "#/definitions/GeneralError"
            },
            "examples" : {
              "application/json" : "{}"
            }
          }
        }
      }
    },
    "/Location/{id}" : {
      "get" : {
        "summary" : "Returns Location details of given id",
        "produces" : [ "application/json", "application/xml", "application/xml+fhir", "application/json+fhir" ],
        "parameters" : [ {
          "name" : "id",
          "in" : "path",
          "description" : "Id of the  Location resource",
          "required" : true,
          "type" : "string"
        } ],
        "responses" : {
          "200" : {
            "description" : "Returns Location details of given id",
            "schema" : {
              "type" : "object",
              "$ref" : "#/definitions/Location"
            },
            "examples" : {
              "application/json" : "{\n  \"resourceType\": \"Location\",\n  \"id\": \"a846f32f-5401-4d53-871a-68354c22c3f9\",\n  \"name\": \"South Wing, second floor\",\n  \"description\": \"Second floor of the Old South Wing, formerly in use by Psychiatry\",\n  \"address\": {\n    \"use\": \"work\",\n    \"line\": [\n      \"Galapagosweg 91, Building A\",\"line 3\", \"line 4\", \"line 5\"\n    ],\n    \"city\": \"Den Burg\",\n    \"postalCode\": \"9105 PZ\",\n    \"country\": \"NLD\",\n    \"state\":\"southern\"\n  },\n  \"position\": {\n    \"longitude\": -83.6945691,\n    \"latitude\": 42.25475478,\n  },\n  \"partOf\": {\n     \"reference\": \"Location/c0937d4f-1691-11df-97a5-7038c432aabf\"\n     \"display\": \"Mosoriot Hospital\"\n  },\n  \"status\": \"active\"\n}\n"
            }
          },
          "404" : {
            "description" : "When error occurred",
            "schema" : {
              "type" : "object",
              "$ref" : "#/definitions/GeneralError"
            },
            "examples" : {
              "application/json" : "{}"
            }
          }
        }
      },
      "delete" : {
        "summary" : "Returns Location details of given id",
        "produces" : [ "application/json", "application/xml", "application/xml+fhir", "application/json+fhir" ],
        "parameters" : [ {
          "name" : "id",
          "in" : "path",
          "description" : "Id of the  Location resource",
          "required" : true,
          "type" : "string"
        } ],
        "responses" : {
          "200" : {
            "description" : "Delete Location details of given id"
          },
          "404" : {
            "description" : "When error occurred",
            "schema" : {
              "type" : "object",
              "$ref" : "#/definitions/GeneralError"
            },
            "examples" : {
              "application/json" : "{}"
            }
          }
        }
      },
      "put" : {
        "summary" : "Update Location resource from the content of the request",
        "produces" : [ "application/json", "application/xml", "application/xml+fhir", "application/json+fhir" ],
        "parameters" : [ {
          "name" : "body",
          "in" : "body",
          "description" : "Location resource object",
          "required" : true,
          "schema" : {
            "$ref" : "#/definitions/Location"
          }
        }, {
          "name" : "id",
          "in" : "path",
          "description" : "Id of the  Location resource",
          "required" : true,
          "type" : "string"
        } ],
        "responses" : {
          "200" : {
            "description" : "Returns success operation outcome",
            "schema" : {
              "type" : "object",
              "$ref" : "#/definitions/OperationOutcome"
            }
          },
          "404" : {
            "description" : "When error occurred",
            "schema" : {
              "type" : "object",
              "$ref" : "#/definitions/GeneralError"
            },
            "examples" : {
              "application/json" : "{}"
            }
          }
        }
      }
    },
    "/Condition/{id}" : {
      "get" : {
        "summary" : "Returns Condition details of given id",
        "produces" : [ "application/json", "application/xml", "application/xml+fhir", "application/json+fhir" ],
        "parameters" : [ {
          "name" : "id",
          "in" : "path",
          "description" : "Id of the  Condition resource",
          "required" : true,
          "type" : "string"
        } ],
        "responses" : {
          "200" : {
            "description" : "Returns Condition details of given id",
            "schema" : {
              "type" : "object",
              "$ref" : "#/definitions/Condition"
            }
          },
          "404" : {
            "description" : "When error occurred",
            "schema" : {
              "type" : "object",
              "$ref" : "#/definitions/GeneralError"
            },
            "examples" : {
              "application/json" : "{}"
            }
          }
        }
      }
    },
    "/DiagnosticReport/{id}" : {
      "get" : {
        "summary" : "Returns DiagnosticReport details of given id",
        "produces" : [ "application/json", "application/xml", "application/xml+fhir", "application/json+fhir" ],
        "parameters" : [ {
          "name" : "id",
          "in" : "path",
          "description" : "Id of the  DiagnosticReport resource",
          "required" : true,
          "type" : "string"
        } ],
        "responses" : {
          "200" : {
            "description" : "Returns DiagnosticReport details of given id",
            "schema" : {
              "type" : "object",
              "$ref" : "#/definitions/DiagnosticReport"
            }
          },
          "404" : {
            "description" : "When error occurred",
            "schema" : {
              "type" : "object",
              "$ref" : "#/definitions/GeneralError"
            },
            "examples" : {
              "application/json" : "{}"
            }
          }
        }
      },
      "delete" : {
        "summary" : "Returns DiagnosticReport details of given id",
        "produces" : [ "application/json", "application/xml", "application/xml+fhir", "application/json+fhir" ],
        "parameters" : [ {
          "name" : "id",
          "in" : "path",
          "description" : "Id of the  DiagnosticReport resource",
          "required" : true,
          "type" : "string"
        } ],
        "responses" : {
          "200" : {
            "description" : "Delete DiagnosticReport details of given id"
          },
          "404" : {
            "description" : "When error occurred",
            "schema" : {
              "type" : "object",
              "$ref" : "#/definitions/GeneralError"
            },
            "examples" : {
              "application/json" : "{}"
            }
          }
        }
      },
      "put" : {
        "summary" : "Update DiagnosticReport resource from the content of the request",
        "produces" : [ "application/json", "application/xml", "application/xml+fhir", "application/json+fhir" ],
        "parameters" : [ {
          "name" : "body",
          "in" : "body",
          "description" : "DiagnosticReport resource object",
          "required" : true,
          "schema" : {
            "$ref" : "#/definitions/DiagnosticReport"
          }
        }, {
          "name" : "id",
          "in" : "path",
          "description" : "Id of the  DiagnosticReport resource",
          "required" : true,
          "type" : "string"
        } ],
        "responses" : {
          "200" : {
            "description" : "Returns success operation outcome",
            "schema" : {
              "type" : "object",
              "$ref" : "#/definitions/OperationOutcome"
            }
          },
          "404" : {
            "description" : "When error occurred",
            "schema" : {
              "type" : "object",
              "$ref" : "#/definitions/GeneralError"
            },
            "examples" : {
              "application/json" : "{}"
            }
          }
        }
      }
    },
    "/Practitioner" : {
      "post" : {
        "summary" : "Create Practitioner resource from the content of the request",
        "produces" : [ "application/json", "application/xml", "application/xml+fhir", "application/json+fhir" ],
        "parameters" : [ {
          "name" : "body",
          "in" : "body",
          "description" : "Practitioner resource object",
          "required" : true,
          "schema" : {
            "$ref" : "#/definitions/Practitioner"
          }
        } ],
        "responses" : {
          "200" : {
            "description" : "Returns success operation outcome",
            "schema" : {
              "type" : "object",
              "$ref" : "#/definitions/OperationOutcome"
            }
          },
          "404" : {
            "description" : "When error occurred",
            "schema" : {
              "type" : "object",
              "$ref" : "#/definitions/GeneralError"
            },
            "examples" : {
              "application/json" : "{}"
            }
          }
        }
      },
      "get" : {
        "summary" : "Returns Practitioner matching results",
        "produces" : [ "application/json", "application/xml", "application/xml+fhir", "application/json+fhir" ],
        "parameters" : [ {
          "name" : "identifier",
          "in" : "query",
          "description" : "A practitioner's Identifier",
          "required" : false,
          "type" : "string"
        }, {
          "name" : "given",
          "in" : "query",
          "description" : "A portion of the given name",
          "required" : false,
          "type" : "string"
        }, {
          "name" : "name",
          "in" : "query",
          "description" : "A portion of either family or given name",
          "required" : false,
          "type" : "string"
        }, {
          "name" : "_id",
          "in" : "query",
          "description" : "The ID of the resource",
          "required" : false,
          "type" : "string"
        }, {
          "name" : "family",
          "in" : "query",
          "description" : "A portion of the family name",
          "required" : false,
          "type" : "string"
        } ],
        "responses" : {
          "200" : {
            "description" : "Bundle of Practitioner resources",
            "schema" : {
              "type" : "array",
              "$ref" : "#/definitions/Practitioner"
            },
            "examples" : {
              "application/json" : "{\n  \"resourceType\": \"Practitioner\",\n  \"id\": \"a846f32f-5401-4d53-871a-68354c22c3f9\",\n  \"identifier\": [\n    {\n      \"system\": \"http://www.acme.org/practitioners\",\n      \"value\": \"clerk\"\n    }\n  ],\n  \"name\": {\n    \"family\": [\n      \"Careful\"\n    ],\n    \"given\": [\n      \"Adam\"\n    ]\n  },\n  \"address\": [\n    {\n      \"use\": \"home\",\n      \"city\": \"E. Kanateng\"\n    }\n  ],\n  \"gender\": {\n    \"coding\": [\n      {\n        \"system\": \"http://hl7.org/fhir/v3/AdministrativeGender\",\n        \"code\": \"M\"\n      }\n    ]\n  },\n  \"birthDate\": \"2009-08-11T00:00:00\"\n}"
            }
          },
          "404" : {
            "description" : "When error occurred",
            "schema" : {
              "type" : "object",
              "$ref" : "#/definitions/GeneralError"
            },
            "examples" : {
              "application/json" : "{}"
            }
          }
        }
      }
    },
    "/Patient/{id}/$everything" : {
      "post" : {
        "summary" : "Returns Patient everything of given id",
        "produces" : [ "application/json", "application/xml", "application/xml+fhir", "application/json+fhir" ],
        "parameters" : [ {
          "name" : "id",
          "in" : "path",
          "description" : "Id of the  Patient resource",
          "required" : true,
          "type" : "string"
        }, {
          "name" : "body",
          "in" : "body",
          "description" : "Patient resource constant body parameter",
          "required" : true,
          "schema" : {
            "$ref" : "#/definitions/Patient"
          }
        } ],
        "responses" : {
          "200" : {
            "description" : "Returns Patient everything of given id",
            "schema" : {
              "type" : "object",
              "$ref" : "#/definitions/Patient"
            }
          },
          "404" : {
            "description" : "When error occurred",
            "schema" : {
              "type" : "object",
              "$ref" : "#/definitions/GeneralError"
            },
            "examples" : {
              "application/json" : "{}"
            }
          }
        }
      }
    },
    "/AllergyIntolerance" : {
      "get" : {
        "summary" : "Returns AllergyIntolerance matching results",
        "produces" : [ "application/json", "application/xml", "application/xml+fhir", "application/json+fhir" ],
        "parameters" : [ {
          "name" : "patient",
          "in" : "query",
          "description" : "",
          "required" : false,
          "type" : "string"
        }, {
          "name" : "_id",
          "in" : "query",
          "description" : "The ID of the resource",
          "required" : false,
          "type" : "string"
        } ],
        "responses" : {
          "200" : {
            "description" : "Bundle of AllergyIntolerance resources",
            "schema" : {
              "type" : "array",
              "$ref" : "#/definitions/AllergyIntolerance"
            },
            "examples" : {
              "application/json" : "{}"
            }
          },
          "404" : {
            "description" : "When error occurred",
            "schema" : {
              "type" : "object",
              "$ref" : "#/definitions/GeneralError"
            },
            "examples" : {
              "application/json" : "{}"
            }
          }
        }
      }
    },
    "/Encounter/{id}" : {
      "get" : {
        "summary" : "Returns Encounter details of given id",
        "produces" : [ "application/json", "application/xml", "application/xml+fhir", "application/json+fhir" ],
        "parameters" : [ {
          "name" : "id",
          "in" : "path",
          "description" : "Id of the  Encounter resource",
          "required" : true,
          "type" : "string"
        } ],
        "responses" : {
          "200" : {
            "description" : "Returns Encounter details of given id",
            "schema" : {
              "type" : "object",
              "$ref" : "#/definitions/Encounter"
            },
            "examples" : {
              "application/json" : "{\n    resourceType: \"Encounter\",\n    status: \"finished\",\n    class: \"inpatient\",\n    subject: {\n        reference: \"Patient/dd738d54-1691-11df-97a5-7038c432aabf\",\n        display: \"Daisylene Ekeno(Identifier:1865TU-8)\"\n    },\n    participant: [{\n            individual: {\n                reference: \"Practitioner/bf218490-1691-11df-97a5-7038c432aabf\",\n                display: \"Super User(Identifier:admin)\"\n            }\n        }],\n    period: {\n        start: \"2006-02-07T00:00:00\",\n        end: \"2006-02-07T00:00:00\"\n    },\n    location: [\n          {\n            location: {\n                reference: \"Location/8d6c993e-c2cc-11de-8d13-0010c6dffd0f\",\n                display: \"Inpatient Ward\"\n            },\n            period: {\n                start: \"2006-02-07T00:00:00\",\n                end: \"2006-02-07T00:00:00\"\n            }\n        }]\n}"
            }
          },
          "404" : {
            "description" : "When error occurred",
            "schema" : {
              "type" : "object",
              "$ref" : "#/definitions/GeneralError"
            },
            "examples" : {
              "application/json" : "{}"
            }
          }
        }
      },
      "delete" : {
        "summary" : "Returns Encounter details of given id",
        "produces" : [ "application/json", "application/xml", "application/xml+fhir", "application/json+fhir" ],
        "parameters" : [ {
          "name" : "id",
          "in" : "path",
          "description" : "Id of the  Encounter resource",
          "required" : true,
          "type" : "string"
        } ],
        "responses" : {
          "200" : {
            "description" : "Delete Encounter details of given id"
          },
          "404" : {
            "description" : "When error occurred",
            "schema" : {
              "type" : "object",
              "$ref" : "#/definitions/GeneralError"
            },
            "examples" : {
              "application/json" : "{}"
            }
          }
        }
      }
    },
    "/Patient" : {
      "post" : {
        "summary" : "Create Patient resource from the content of the request",
        "produces" : [ "application/json", "application/xml", "application/xml+fhir", "application/json+fhir" ],
        "parameters" : [ {
          "name" : "body",
          "in" : "body",
          "description" : "Patient resource object",
          "required" : true,
          "schema" : {
            "$ref" : "#/definitions/Patient"
          }
        } ],
        "responses" : {
          "200" : {
            "description" : "Returns success operation outcome",
            "schema" : {
              "type" : "object",
              "$ref" : "#/definitions/OperationOutcome"
            }
          },
          "404" : {
            "description" : "When error occurred",
            "schema" : {
              "type" : "object",
              "$ref" : "#/definitions/GeneralError"
            },
            "examples" : {
              "application/json" : "{}"
            }
          }
        }
      },
      "get" : {
        "summary" : "Returns Patient matching results",
        "produces" : [ "application/json", "application/xml", "application/xml+fhir", "application/json+fhir" ],
        "parameters" : [ {
          "name" : "careprovider",
          "in" : "query",
          "description" : "Patient's nominated care provider, could be a care manager, not the organization that manages the record",
          "required" : false,
          "type" : "string"
        }, {
          "name" : "identifier",
          "in" : "query",
          "description" : "A patient identifier",
          "required" : false,
          "type" : "string"
        }, {
          "name" : "given",
          "in" : "query",
          "description" : "A portion of the given name of the patient",
          "required" : false,
          "type" : "string"
        }, {
          "name" : "name",
          "in" : "query",
          "description" : "A portion of either family or given name of the patient",
          "required" : false,
          "type" : "string"
        }, {
          "name" : "active",
          "in" : "query",
          "description" : "Whether the patient record is active",
          "required" : false,
          "type" : "string"
        }, {
          "name" : "_id",
          "in" : "query",
          "description" : "The ID of the resource",
          "required" : false,
          "type" : "string"
        }, {
          "name" : "family",
          "in" : "query",
          "description" : "A portion of the family name of the patient",
          "required" : false,
          "type" : "string"
        } ],
        "responses" : {
          "200" : {
            "description" : "Bundle of Patient resources",
            "schema" : {
              "type" : "array",
              "$ref" : "#/definitions/Patient"
            },
            "examples" : {
              "application/json" : "{\n  \"resourceType\": \"Patient\",\n  \"id\": \"example\",\n  \"identifier\": [\n    {\n      \"use\": \"usual\",\n      \"label\": \"MRN\",\n      \"system\": \"urn:oid:1.2.36.146.595.217.0.1\",\n      \"value\": \"12345\",\n      \"period\": {\n        \"start\": \"2001-05-06\"\n      },\n      \"assigner\": {\n        \"display\": \"Acme Healthcare\"\n      }\n    }\n  ],\n  \"name\": [\n    {\n      \"use\": \"official\",\n      \"family\": [\n        \"Chalmers\"\n      ],\n      \"given\": [\n        \"Peter\",\n        \"James\"\n      ]\n    },\n    {\n      \"use\": \"usual\",\n      \"given\": [\n        \"Jim\"\n      ]\n    }\n  ],\n  \"telecom\": [\n    {\n      \"use\": \"home\"\n    },\n    {\n      \"system\": \"phone\",\n      \"value\": \"(03) 5555 6473\",\n      \"use\": \"work\"\n    }\n  ],\n  \"gender\": \"male\",\n  \"birthDate\": \"1974-12-25\",\n  \"deceasedBoolean\": false,\n  \"address\": [\n    {\n      \"use\": \"home\",\n      \"line\": [\n        \"534 Erewhon St\"\n      ],\n      \"city\": \"PleasantVille\",\n      \"state\": \"Vic\",\n      \"postalCode\": \"3999\"\n    }\n  ],\n  \"active\": true\n}"
            }
          },
          "404" : {
            "description" : "When error occurred",
            "schema" : {
              "type" : "object",
              "$ref" : "#/definitions/GeneralError"
            },
            "examples" : {
              "application/json" : "{}"
            }
          }
        }
      }
    },
    "/Patient/{id}" : {
      "get" : {
        "summary" : "Returns Patient details of given id",
        "produces" : [ "application/json", "application/xml", "application/xml+fhir", "application/json+fhir" ],
        "parameters" : [ {
          "name" : "id",
          "in" : "path",
          "description" : "Id of the  Patient resource",
          "required" : true,
          "type" : "string"
        } ],
        "responses" : {
          "200" : {
            "description" : "Returns Patient details of given id",
            "schema" : {
              "type" : "object",
              "$ref" : "#/definitions/Patient"
            },
            "examples" : {
              "application/json" : "{\n  \"resourceType\": \"Patient\",\n  \"id\": \"example\",\n  \"identifier\": [\n    {\n      \"use\": \"usual\",\n      \"label\": \"MRN\",\n      \"system\": \"urn:oid:1.2.36.146.595.217.0.1\",\n      \"value\": \"12345\",\n      \"period\": {\n        \"start\": \"2001-05-06\"\n      },\n      \"assigner\": {\n        \"display\": \"Acme Healthcare\"\n      }\n    }\n  ],\n  \"name\": [\n    {\n      \"use\": \"official\",\n      \"family\": [\n        \"Chalmers\"\n      ],\n      \"given\": [\n        \"Peter\",\n        \"James\"\n      ]\n    },\n    {\n      \"use\": \"usual\",\n      \"given\": [\n        \"Jim\"\n      ]\n    }\n  ],\n  \"telecom\": [\n    {\n      \"use\": \"home\"\n    },\n    {\n      \"system\": \"phone\",\n      \"value\": \"(03) 5555 6473\",\n      \"use\": \"work\"\n    }\n  ],\n  \"gender\": \"male\",\n  \"birthDate\": \"1974-12-25\",\n  \"deceasedBoolean\": false,\n  \"address\": [\n    {\n      \"use\": \"home\",\n      \"line\": [\n        \"534 Erewhon St\"\n      ],\n      \"city\": \"PleasantVille\",\n      \"state\": \"Vic\",\n      \"postalCode\": \"3999\"\n    }\n  ],\n  \"active\": true\n}"
            }
          },
          "404" : {
            "description" : "When error occurred",
            "schema" : {
              "type" : "object",
              "$ref" : "#/definitions/GeneralError"
            },
            "examples" : {
              "application/json" : "{}"
            }
          }
        }
      },
      "delete" : {
        "summary" : "Returns Patient details of given id",
        "produces" : [ "application/json", "application/xml", "application/xml+fhir", "application/json+fhir" ],
        "parameters" : [ {
          "name" : "id",
          "in" : "path",
          "description" : "Id of the  Patient resource",
          "required" : true,
          "type" : "string"
        } ],
        "responses" : {
          "200" : {
            "description" : "Delete Patient details of given id"
          },
          "404" : {
            "description" : "When error occurred",
            "schema" : {
              "type" : "object",
              "$ref" : "#/definitions/GeneralError"
            },
            "examples" : {
              "application/json" : "{}"
            }
          }
        }
      },
      "put" : {
        "summary" : "Update Patient resource from the content of the request",
        "produces" : [ "application/json", "application/xml", "application/xml+fhir", "application/json+fhir" ],
        "parameters" : [ {
          "name" : "body",
          "in" : "body",
          "description" : "Patient resource object",
          "required" : true,
          "schema" : {
            "$ref" : "#/definitions/Patient"
          }
        }, {
          "name" : "id",
          "in" : "path",
          "description" : "Id of the  Patient resource",
          "required" : true,
          "type" : "string"
        } ],
        "responses" : {
          "200" : {
            "description" : "Returns success operation outcome",
            "schema" : {
              "type" : "object",
              "$ref" : "#/definitions/OperationOutcome"
            }
          },
          "404" : {
            "description" : "When error occurred",
            "schema" : {
              "type" : "object",
              "$ref" : "#/definitions/GeneralError"
            },
            "examples" : {
              "application/json" : "{}"
            }
          }
        }
      }
    },
    "/Person/{id}" : {
      "get" : {
        "summary" : "Returns Person details of given id",
        "produces" : [ "application/json", "application/xml", "application/xml+fhir", "application/json+fhir" ],
        "parameters" : [ {
          "name" : "id",
          "in" : "path",
          "description" : "Id of the  Person resource",
          "required" : true,
          "type" : "string"
        } ],
        "responses" : {
          "200" : {
            "description" : "Returns Person details of given id",
            "schema" : {
              "type" : "object",
              "$ref" : "#/definitions/Person"
            },
            "examples" : {
              "application/json" : "{\n  \"resourceType\": \"Person\",\n  \"id\": \"dda12af7-1691-11df-97a5-7038c432aabf\",\n  \"name\": [\n    {\n      \"use\": \"official\",\n      \"family\": [\n        \"Chalmers\"\n      ],\n      \"given\": [\n        \"Peter\",\n        \"James\"\n      ]\n    },\n    {\n      \"use\": \"usual\",\n      \"given\": [\n        \"Jim\"\n      ]\n    }\n  ],\n  \"gender\": \"male\",\n  \"birthDate\": \"1974-12-25\",\n  \"address\": [\n    {\n      \"use\": \"home\",\n      \"line\": [\n        \"534 Erewhon St\"\n      ],\n      \"city\": \"PleasantVille\",\n      \"state\": \"Vic\",\n      \"postalCode\": \"3999\"\n    }\n  ],\n  \"active\": true\n}"
            }
          },
          "404" : {
            "description" : "When error occurred",
            "schema" : {
              "type" : "object",
              "$ref" : "#/definitions/GeneralError"
            },
            "examples" : {
              "application/json" : "{}"
            }
          }
        }
      },
      "delete" : {
        "summary" : "Returns Person details of given id",
        "produces" : [ "application/json", "application/xml", "application/xml+fhir", "application/json+fhir" ],
        "parameters" : [ {
          "name" : "id",
          "in" : "path",
          "description" : "Id of the  Person resource",
          "required" : true,
          "type" : "string"
        } ],
        "responses" : {
          "200" : {
            "description" : "Delete Person details of given id"
          },
          "404" : {
            "description" : "When error occurred",
            "schema" : {
              "type" : "object",
              "$ref" : "#/definitions/GeneralError"
            },
            "examples" : {
              "application/json" : "{}"
            }
          }
        }
      },
      "put" : {
        "summary" : "Update Person resource from the content of the request",
        "produces" : [ "application/json", "application/xml", "application/xml+fhir", "application/json+fhir" ],
        "parameters" : [ {
          "name" : "body",
          "in" : "body",
          "description" : "Person resource object",
          "required" : true,
          "schema" : {
            "$ref" : "#/definitions/Person"
          }
        }, {
          "name" : "id",
          "in" : "path",
          "description" : "Id of the  Person resource",
          "required" : true,
          "type" : "string"
        } ],
        "responses" : {
          "200" : {
            "description" : "Returns success operation outcome",
            "schema" : {
              "type" : "object",
              "$ref" : "#/definitions/OperationOutcome"
            }
          },
          "404" : {
            "description" : "When error occurred",
            "schema" : {
              "type" : "object",
              "$ref" : "#/definitions/GeneralError"
            },
            "examples" : {
              "application/json" : "{}"
            }
          }
        }
      }
    },
    "/Condition" : {
      "get" : {
        "summary" : "Returns Condition matching results",
        "produces" : [ "application/json", "application/xml", "application/xml+fhir", "application/json+fhir" ],
        "parameters" : [ {
          "name" : "patient",
          "in" : "query",
          "description" : "",
          "required" : false,
          "type" : "string"
        }, {
          "name" : "_id",
          "in" : "query",
          "description" : "The ID of the resource",
          "required" : false,
          "type" : "string"
        } ],
        "responses" : {
          "200" : {
            "description" : "Bundle of Condition resources",
            "schema" : {
              "type" : "array",
              "$ref" : "#/definitions/Condition"
            }
          },
          "404" : {
            "description" : "When error occurred",
            "schema" : {
              "type" : "object",
              "$ref" : "#/definitions/GeneralError"
            },
            "examples" : {
              "application/json" : "{}"
            }
          }
        }
      }
    },
    "/FamilyMemberHistory" : {
      "get" : {
        "summary" : "Returns FamilyMemberHistory matching results",
        "produces" : [ "application/json", "application/xml", "application/xml+fhir", "application/json+fhir" ],
        "parameters" : [ {
          "name" : "patient",
          "in" : "query",
          "description" : "The identity of a subject to list family member history items for",
          "required" : false,
          "type" : "string"
        }, {
          "name" : "_id",
          "in" : "query",
          "description" : "The ID of the resource",
          "required" : false,
          "type" : "string"
        } ],
        "responses" : {
          "200" : {
            "description" : "Bundle of FamilyMemberHistory resources",
            "schema" : {
              "type" : "array",
              "$ref" : "#/definitions/FamilyMemberHistory"
            },
            "examples" : {
              "application/json" : "{\n  \"resourceType\": \"FamilyHistory\",\n  \"id\": \"dda12af7-1691-11df-97a5-7038c432aabf\",\n  \"patient\": {\n    \"reference\": \"Patient/example\",\n    \"display\": \"Peter Patient\"\n  },\n  \"relation\": [\n    {\n      \"relationship\": {\n        \"coding\": [\n          {\n            \"system\": \"http://hl7.org/fhir/familial-relationship\",\n            \"code\": \"father\"\n          }\n        ]\n      },\n      \"condition\": [\n        {\n          \"type\": {\n            \"coding\": [\n              {\n                \"system\": \"http://snomed.info/sct\",\n                \"code\": \"315619001\",\n                \"display\": \"Myocardial Infarction\"\n              }\n            ],\n            \"text\": \"Heart Attack\"\n          },\n          \"onsetAge\": {\n            \"value\": 74,\n            \"units\": \"a\",\n            \"system\": \"http://unitsofmeasure.org\"\n          },\n          \"note\": \"Was fishing at the time. At least he went doing someting he loved.\"\n        }\n      ]\n    }\n  ]\n}"
            }
          },
          "404" : {
            "description" : "When error occurred",
            "schema" : {
              "type" : "object",
              "$ref" : "#/definitions/GeneralError"
            },
            "examples" : {
              "application/json" : "{}"
            }
          }
        }
      }
    },
    "/Location" : {
      "post" : {
        "summary" : "Create Location resource from the content of the request",
        "produces" : [ "application/json", "application/xml", "application/xml+fhir", "application/json+fhir" ],
        "parameters" : [ {
          "name" : "body",
          "in" : "body",
          "description" : "Location resource object",
          "required" : true,
          "schema" : {
            "$ref" : "#/definitions/Location"
          }
        } ],
        "responses" : {
          "200" : {
            "description" : "Returns success operation outcome",
            "schema" : {
              "type" : "object",
              "$ref" : "#/definitions/OperationOutcome"
            }
          },
          "404" : {
            "description" : "When error occurred",
            "schema" : {
              "type" : "object",
              "$ref" : "#/definitions/GeneralError"
            },
            "examples" : {
              "application/json" : "{}"
            }
          }
        }
      },
      "get" : {
        "summary" : "Returns Location matching results",
        "produces" : [ "application/json", "application/xml", "application/xml+fhir", "application/json+fhir" ],
        "parameters" : [ {
          "name" : "name",
          "in" : "query",
          "description" : "A (portion of the) name of the location",
          "required" : false,
          "type" : "string"
        }, {
          "name" : "_id",
          "in" : "query",
          "description" : "The ID of the resource",
          "required" : false,
          "type" : "string"
        }, {
          "name" : "status",
          "in" : "query",
          "description" : "Searches for locations with a specific kind of status",
          "required" : false,
          "type" : "string"
        } ],
        "responses" : {
          "200" : {
            "description" : "Bundle of Location resources",
            "schema" : {
              "type" : "array",
              "$ref" : "#/definitions/Location"
            },
            "examples" : {
              "application/json" : "{\n  \"resourceType\": \"Location\",\n  \"id\": \"a846f32f-5401-4d53-871a-68354c22c3f9\",\n  \"name\": \"South Wing, second floor\",\n  \"description\": \"Second floor of the Old South Wing, formerly in use by Psychiatry\",\n  \"address\": {\n    \"use\": \"work\",\n    \"line\": [\n      \"Galapagosweg 91, Building A\",\"line 3\", \"line 4\", \"line 5\"\n    ],\n    \"city\": \"Den Burg\",\n    \"postalCode\": \"9105 PZ\",\n    \"country\": \"NLD\",\n    \"state\":\"southern\"\n  },\n  \"position\": {\n    \"longitude\": -83.6945691,\n    \"latitude\": 42.25475478,\n  },\n  \"partOf\": {\n     \"reference\": \"Location/c0937d4f-1691-11df-97a5-7038c432aabf\"\n     \"display\": \"Mosoriot Hospital\"\n  },\n  \"status\": \"active\"\n}\n"
            }
          },
          "404" : {
            "description" : "When error occurred",
            "schema" : {
              "type" : "object",
              "$ref" : "#/definitions/GeneralError"
            },
            "examples" : {
              "application/json" : "{}"
            }
          }
        }
      }
    },
    "/Practitioner/{id}" : {
      "get" : {
        "summary" : "Returns Practitioner details of given id",
        "produces" : [ "application/json", "application/xml", "application/xml+fhir", "application/json+fhir" ],
        "parameters" : [ {
          "name" : "id",
          "in" : "path",
          "description" : "Id of the  Practitioner resource",
          "required" : true,
          "type" : "string"
        } ],
        "responses" : {
          "200" : {
            "description" : "Returns Practitioner details of given id",
            "schema" : {
              "type" : "object",
              "$ref" : "#/definitions/Practitioner"
            },
            "examples" : {
              "application/json" : "{\n  \"resourceType\": \"Practitioner\",\n  \"id\": \"a846f32f-5401-4d53-871a-68354c22c3f9\",\n  \"identifier\": [\n    {\n      \"system\": \"http://www.acme.org/practitioners\",\n      \"value\": \"clerk\"\n    }\n  ],\n  \"name\": {\n    \"family\": [\n      \"Careful\"\n    ],\n    \"given\": [\n      \"Adam\"\n    ]\n  },\n  \"address\": [\n    {\n      \"use\": \"home\",\n      \"city\": \"E. Kanateng\"\n    }\n  ],\n  \"gender\": {\n    \"coding\": [\n      {\n        \"system\": \"http://hl7.org/fhir/v3/AdministrativeGender\",\n        \"code\": \"M\"\n      }\n    ]\n  },\n  \"birthDate\": \"2009-08-11T00:00:00\"\n}"
            }
          },
          "404" : {
            "description" : "When error occurred",
            "schema" : {
              "type" : "object",
              "$ref" : "#/definitions/GeneralError"
            },
            "examples" : {
              "application/json" : "{}"
            }
          }
        }
      }
    },
    "/Encounter/{id}/$everything" : {
      "post" : {
        "summary" : "Returns Encounter everything of given id",
        "produces" : [ "application/json", "application/xml", "application/xml+fhir", "application/json+fhir" ],
        "parameters" : [ {
          "name" : "id",
          "in" : "path",
          "description" : "Id of the  Encounter resource",
          "required" : true,
          "type" : "string"
        }, {
          "name" : "body",
          "in" : "body",
          "description" : "Encounter resource constant body parameter",
          "required" : true,
          "schema" : {
            "$ref" : "#/definitions/Encounter"
          }
        } ],
        "responses" : {
          "200" : {
            "description" : "Returns Encounter everything of given id",
            "schema" : {
              "type" : "object",
              "$ref" : "#/definitions/Encounter"
            }
          },
          "404" : {
            "description" : "When error occurred",
            "schema" : {
              "type" : "object",
              "$ref" : "#/definitions/GeneralError"
            },
            "examples" : {
              "application/json" : "{}"
            }
          }
        }
      }
    }
  },
  "definitions" : {
    "Condition" : {
      "type" : "object"
    },
    "Bundle" : {
      "type" : "object"
    },
    "DiagnosticReport" : {
      "type" : "object"
    },
    "Patient" : {
      "type" : "object"
    },
    "Practitioner" : {
      "type" : "object"
    },
    "AllergyIntolerance" : {
      "type" : "object"
    },
    "FamilyMemberHistory" : {
      "type" : "object"
    },
    "OperationOutcome" : {
      "type" : "object"
    },
    "Observation" : {
      "type" : "object"
    },
    "Encounter" : {
      "type" : "object"
    },
    "Person" : {
      "type" : "object"
    },
    "GeneralError" : {
      "type" : "object"
    },
    "Location" : {
      "type" : "object"
    }
  },
  "externalDocs" : {
    "description" : "Find more info here",
    "url" : "https://wiki.openmrs.org/display/projects/OpenMRS+FHIR+Module"
  },
  "parameters" : {
    "formatParam" : {
      "name" : "_format",
      "in" : "query",
      "description" : "Format parameter can use to get response by setting _fromat param value  from xml by _format=xml and response from json by _format=json",
      "required" : false,
      "type" : "string"
    }
  }
}
